102383058_calculator/__init__.py
calculator/__init__.py
102383058_calculator-0.1.dist-info/LICENSES.txt
102383058_calculator-0.1.dist-info/METADATA
102383058_calculator-0.1.dist-info/WHEEL
102383058_calculator-0.1.dist-info/top_level.txt
102383058_calculator-0.1.dist-info/RECORD
