Metadata-Version: 2.2
Name: 102383058_calculator
Version: 0.1
Summary: This is very basic calculator
Author: Shaambhavi Sharma
Author-email: shaambhavi05@gmail.com
Classifier: Programming Language :: Python :: 3
Classifier: License :: OSI Approved :: MIT License
Classifier: Operating System :: OS Independent
License-File: LICENSES.txt
Dynamic: author
Dynamic: author-email
Dynamic: classifier
Dynamic: summary
